FlightFinderApp_JG/Constants.py
FlightFinderApp_JG/DestinationManager.py
FlightFinderApp_JG/FlightManager.py
FlightFinderApp_JG/SessionManager.py
FlightFinderApp_JG/__Parsers.py
FlightFinderApp_JG/__init__.py
FlightFinderApp_JG/cli.py
flightfinderapp_jg-0.1.7.dist-info/METADATA
flightfinderapp_jg-0.1.7.dist-info/WHEEL
flightfinderapp_jg-0.1.7.dist-info/entry_points.txt
flightfinderapp_jg-0.1.7.dist-info/licenses/LICENSE
flightfinderapp_jg-0.1.7.dist-info/RECORD
