Metadata-Version: 2.3
Name: FlightFinderApp_JG
Version: 0.1.7
Summary: A helper that interacts with low-cost air carrier's API and helps to find cheap flights.
Project-URL: Homepage, https://github.com/jgreibus/flight_finder
Project-URL: Issues, https://github.com/jgreibus/flight_finder/issues
Author: Justinas Greibus
License-File: LICENSE
Classifier: Development Status :: 4 - Beta
Classifier: License :: OSI Approved :: MIT License
Classifier: Operating System :: OS Independent
Classifier: Programming Language :: Python :: 3
Requires-Python: >=3.6
